sql2arrow-0.1.3.dist-info/METADATA
sql2arrow-0.1.3.dist-info/WHEEL
sql2arrow-0.1.3.dist-info/licenses/LICENSE_APACHE
sql2arrow-0.1.3.dist-info/licenses/LICENSE_MIT
sql2arrow/partition.py
sql2arrow/__init__.py
sql2arrow/sql2arrow.abi3.so
sql2arrow-0.1.3.dist-info/RECORD
