Metadata-Version: 2.4
Name: sql2arrow
Version: 0.1.3
Classifier: Development Status :: 4 - Beta
Classifier: Programming Language :: Rust
Classifier: Programming Language :: Python
Classifier: Environment :: Console
License-File: LICENSE_APACHE
License-File: LICENSE_MIT
Summary: This is a Python library that provides convenient and high-performance methods to parse INSERT SQL statements into Arrow arrays.
Keywords: arrow,sql,mysql,rust
Author: zhan zhang
Author-email: goalzz85@gmail.com
Maintainer-email: zhan zhang <goalzz85@gmail.com>
Requires-Python: >=3.8
Project-URL: homepage, https://github.com/goalzz85/sql2arrow
